{
  "gitSyncId": "6553700b0e889e00172e46bf_6571a884ab243c351136f063",
  "id": "Page1_Query1",
  "pluginId": "postgres-plugin",
  "pluginType": "DB",
  "unpublishedAction": {
    "actionConfiguration": {
      "body": "SELECT * FROM <<your_table_name>> LIIT 10;\n\n-- Please enter a valid table name and hit RUN\n",
      "encodeParamsToggle": true,
      "paginationType": "NONE",
      "pluginSpecifiedTemplates": [
        {
          "value": true
        }
      ],
      "timeoutInMillisecond": 10000
    },
    "confirmBeforeExecute": false,
    "datasource": {
      "id": "customer support dashboard",
      "isAutoGenerated": false,
      "name": "customer support dashboard",
      "pluginId": "postgres-plugin"
    },
    "dynamicBindingPathList": [],
    "executeOnLoad": false,
    "name": "Query1",
    "pageId": "Page1",
    "userSetOnLoad": false
  }
}